{
    "_links": {
        "comments": {
            "href": "https://api.github.com/repos/cython/cython/issues/3828/comments"
        },
        "commits": {
            "href": "https://api.github.com/repos/cython/cython/pulls/3828/commits"
        },
        "html": {
            "href": "https://github.com/cython/cython/pull/3828"
        },
        "issue": {
            "href": "https://api.github.com/repos/cython/cython/issues/3828"
        },
        "review_comment": {
            "href": "https://api.github.com/repos/cython/cython/pulls/comments{/number}"
        },
        "review_comments": {
            "href": "https://api.github.com/repos/cython/cython/pulls/3828/comments"
        },
        "self": {
            "href": "https://api.github.com/repos/cython/cython/pulls/3828"
        },
        "statuses": {
            "href": "https://api.github.com/repos/cython/cython/statuses/028af30bdd1781703a26788e0ce479b81923cdf5"
        }
    },
    "active_lock_reason": null,
    "assignee": null,
    "assignees": [],
    "author_association": "FIRST_TIME_CONTRIBUTOR",
    "base": {
        "label": "cython:master",
        "ref": "master",
        "repo": {
            "archive_url": "https://api.github.com/repos/cython/cython/{archive_format}{/ref}",
            "archived": false,
            "assignees_url": "https://api.github.com/repos/cython/cython/assignees{/user}",
            "blobs_url": "https://api.github.com/repos/cython/cython/git/blobs{/sha}",
            "branches_url": "https://api.github.com/repos/cython/cython/branches{/branch}",
            "clone_url": "https://github.com/cython/cython.git",
            "collaborators_url": "https://api.github.com/repos/cython/cython/collaborators{/collaborator}",
            "comments_url": "https://api.github.com/repos/cython/cython/comments{/number}",
            "commits_url": "https://api.github.com/repos/cython/cython/commits{/sha}",
            "compare_url": "https://api.github.com/repos/cython/cython/compare/{base}...{head}",
            "contents_url": "https://api.github.com/repos/cython/cython/contents/{+path}",
            "contributors_url": "https://api.github.com/repos/cython/cython/contributors",
            "created_at": "2010-11-21T07:44:20Z",
            "default_branch": "master",
            "deployments_url": "https://api.github.com/repos/cython/cython/deployments",
            "description": "The most widely used Python to C compiler",
            "disabled": false,
            "downloads_url": "https://api.github.com/repos/cython/cython/downloads",
            "events_url": "https://api.github.com/repos/cython/cython/events",
            "fork": false,
            "forks": 1073,
            "forks_count": 1073,
            "forks_url": "https://api.github.com/repos/cython/cython/forks",
            "full_name": "cython/cython",
            "git_commits_url": "https://api.github.com/repos/cython/cython/git/commits{/sha}",
            "git_refs_url": "https://api.github.com/repos/cython/cython/git/refs{/sha}",
            "git_tags_url": "https://api.github.com/repos/cython/cython/git/tags{/sha}",
            "git_url": "git://github.com/cython/cython.git",
            "has_downloads": true,
            "has_issues": true,
            "has_pages": false,
            "has_projects": true,
            "has_wiki": true,
            "homepage": "https://cython.org",
            "hooks_url": "https://api.github.com/repos/cython/cython/hooks",
            "html_url": "https://github.com/cython/cython",
            "id": 1099265,
            "issue_comment_url": "https://api.github.com/repos/cython/cython/issues/comments{/number}",
            "issue_events_url": "https://api.github.com/repos/cython/cython/issues/events{/number}",
            "issues_url": "https://api.github.com/repos/cython/cython/issues{/number}",
            "keys_url": "https://api.github.com/repos/cython/cython/keys{/key_id}",
            "labels_url": "https://api.github.com/repos/cython/cython/labels{/name}",
            "language": "Python",
            "languages_url": "https://api.github.com/repos/cython/cython/languages",
            "license": {
                "key": "other",
                "name": "Other",
                "node_id": "MDc6TGljZW5zZTA=",
                "spdx_id": "NOASSERTION",
                "url": null
            },
            "merges_url": "https://api.github.com/repos/cython/cython/merges",
            "milestones_url": "https://api.github.com/repos/cython/cython/milestones{/number}",
            "mirror_url": null,
            "name": "cython",
            "node_id": "MDEwOlJlcG9zaXRvcnkxMDk5MjY1",
            "notifications_url": "https://api.github.com/repos/cython/cython/notifications{?since,all,participating}",
            "open_issues": 891,
            "open_issues_count": 891,
            "owner": {
                "avatar_url": "https://avatars3.githubusercontent.com/u/486082?v=4",
                "events_url": "https://api.github.com/users/cython/events{/privacy}",
                "followers_url": "https://api.github.com/users/cython/followers",
                "following_url": "https://api.github.com/users/cython/following{/other_user}",
                "gists_url": "https://api.github.com/users/cython/gists{/gist_id}",
                "gravatar_id": "",
                "html_url": "https://github.com/cython",
                "id": 486082,
                "login": "cython",
                "node_id": "MDEyOk9yZ2FuaXphdGlvbjQ4NjA4Mg==",
                "organizations_url": "https://api.github.com/users/cython/orgs",
                "received_events_url": "https://api.github.com/users/cython/received_events",
                "repos_url": "https://api.github.com/users/cython/repos",
                "site_admin": false,
                "starred_url": "https://api.github.com/users/cython/starred{/owner}{/repo}",
                "subscriptions_url": "https://api.github.com/users/cython/subscriptions",
                "type": "Organization",
                "url": "https://api.github.com/users/cython"
            },
            "private": false,
            "pulls_url": "https://api.github.com/repos/cython/cython/pulls{/number}",
            "pushed_at": "2020-09-23T17:42:52Z",
            "releases_url": "https://api.github.com/repos/cython/cython/releases{/id}",
            "size": 60429,
            "ssh_url": "git@github.com:cython/cython.git",
            "stargazers_count": 5453,
            "stargazers_url": "https://api.github.com/repos/cython/cython/stargazers",
            "statuses_url": "https://api.github.com/repos/cython/cython/statuses/{sha}",
            "subscribers_url": "https://api.github.com/repos/cython/cython/subscribers",
            "subscription_url": "https://api.github.com/repos/cython/cython/subscription",
            "svn_url": "https://github.com/cython/cython",
            "tags_url": "https://api.github.com/repos/cython/cython/tags",
            "teams_url": "https://api.github.com/repos/cython/cython/teams",
            "trees_url": "https://api.github.com/repos/cython/cython/git/trees{/sha}",
            "updated_at": "2020-09-24T07:00:40Z",
            "url": "https://api.github.com/repos/cython/cython",
            "watchers": 5453,
            "watchers_count": 5453
        },
        "sha": "aa8b0d9b89030c0b9ace5698ae5131c623acefa4",
        "user": {
            "avatar_url": "https://avatars3.githubusercontent.com/u/486082?v=4",
            "events_url": "https://api.github.com/users/cython/events{/privacy}",
            "followers_url": "https://api.github.com/users/cython/followers",
            "following_url": "https://api.github.com/users/cython/following{/other_user}",
            "gists_url": "https://api.github.com/users/cython/gists{/gist_id}",
            "gravatar_id": "",
            "html_url": "https://github.com/cython",
            "id": 486082,
            "login": "cython",
            "node_id": "MDEyOk9yZ2FuaXphdGlvbjQ4NjA4Mg==",
            "organizations_url": "https://api.github.com/users/cython/orgs",
            "received_events_url": "https://api.github.com/users/cython/received_events",
            "repos_url": "https://api.github.com/users/cython/repos",
            "site_admin": false,
            "starred_url": "https://api.github.com/users/cython/starred{/owner}{/repo}",
            "subscriptions_url": "https://api.github.com/users/cython/subscriptions",
            "type": "Organization",
            "url": "https://api.github.com/users/cython"
        }
    },
    "body": "The implementation of the Python-style `for ... in` loop over an iterable cpp sequence (using `begin()` and `end()`) needs to determine whether the sequence should be stored in a temporary variable or if it can be iterated over directly.\r\n\r\nThe previous code assumed that attributes are always safe to be iterated directly, but attributes can depend on an rvalue, as in:\r\n\r\n    for i in returns_object_with_vector_attribute().vector:\r\n        ...\r\n\r\nIn such a case we need to store the `in` operand in a temporary value on which `begin()` and `end()` can be safely called.\r\n\r\nIt might make sense to move the test into tests/run/cpp_iterators",
    "closed_at": null,
    "comment_data": [],
    "comments_url": "https://api.github.com/repos/cython/cython/issues/3828/comments",
    "commit_data": [
        {
            "author": {
                "avatar_url": "https://avatars3.githubusercontent.com/u/48094549?v=4",
                "events_url": "https://api.github.com/users/xavth/events{/privacy}",
                "followers_url": "https://api.github.com/users/xavth/followers",
                "following_url": "https://api.github.com/users/xavth/following{/other_user}",
                "gists_url": "https://api.github.com/users/xavth/gists{/gist_id}",
                "gravatar_id": "",
                "html_url": "https://github.com/xavth",
                "id": 48094549,
                "login": "xavth",
                "node_id": "MDQ6VXNlcjQ4MDk0NTQ5",
                "organizations_url": "https://api.github.com/users/xavth/orgs",
                "received_events_url": "https://api.github.com/users/xavth/received_events",
                "repos_url": "https://api.github.com/users/xavth/repos",
                "site_admin": false,
                "starred_url": "https://api.github.com/users/xavth/starred{/owner}{/repo}",
                "subscriptions_url": "https://api.github.com/users/xavth/subscriptions",
                "type": "User",
                "url": "https://api.github.com/users/xavth"
            },
            "comments_url": "https://api.github.com/repos/cython/cython/commits/ff546cd63230ab8ddf7cbd6993e00176538ce049/comments",
            "commit": {
                "author": {
                    "date": "2020-09-14T14:14:11Z",
                    "email": "xavier.thompsonkeyl@gmail.com",
                    "name": "Xavier Thompson"
                },
                "comment_count": 0,
                "committer": {
                    "date": "2020-09-15T12:29:29Z",
                    "email": "xavier.thompsonkeyl@gmail.com",
                    "name": "Xavier Thompson"
                },
                "message": "Fix bug in cpp iteration over rvalue-dependant attribute\n\nThe implementation of the Python-style `for ... in` loop over an\niterable cpp sequence (using `begin()` and `end()`) needs to determine\nwhether the sequence should be stored in a temporary variable or\nif it can be iterated over directly.\n\nThe previous code assumed that attributes are always safe to be\niterated directly, but attributes can depend on an rvalue, as in:\n\n    for i in returns_object_with_vector_attribute().vector:\n        ...\n\nIn such a case we need to store the `in` operand in a temporary value\non which `begin()` and `end()` can be safely called.\n\nIt might make sense to move the test into tests/run/cpp_iterators",
                "tree": {
                    "sha": "cf0a5a5d651e8fbedbbb472de48abc5e31ae7225",
                    "url": "https://api.github.com/repos/cython/cython/git/trees/cf0a5a5d651e8fbedbbb472de48abc5e31ae7225"
                },
                "url": "https://api.github.com/repos/cython/cython/git/commits/ff546cd63230ab8ddf7cbd6993e00176538ce049",
                "verification": {
                    "payload": null,
                    "reason": "unsigned",
                    "signature": null,
                    "verified": false
                }
            },
            "committer": {
                "avatar_url": "https://avatars3.githubusercontent.com/u/48094549?v=4",
                "events_url": "https://api.github.com/users/xavth/events{/privacy}",
                "followers_url": "https://api.github.com/users/xavth/followers",
                "following_url": "https://api.github.com/users/xavth/following{/other_user}",
                "gists_url": "https://api.github.com/users/xavth/gists{/gist_id}",
                "gravatar_id": "",
                "html_url": "https://github.com/xavth",
                "id": 48094549,
                "login": "xavth",
                "node_id": "MDQ6VXNlcjQ4MDk0NTQ5",
                "organizations_url": "https://api.github.com/users/xavth/orgs",
                "received_events_url": "https://api.github.com/users/xavth/received_events",
                "repos_url": "https://api.github.com/users/xavth/repos",
                "site_admin": false,
                "starred_url": "https://api.github.com/users/xavth/starred{/owner}{/repo}",
                "subscriptions_url": "https://api.github.com/users/xavth/subscriptions",
                "type": "User",
                "url": "https://api.github.com/users/xavth"
            },
            "html_url": "https://github.com/cython/cython/commit/ff546cd63230ab8ddf7cbd6993e00176538ce049",
            "node_id": "MDY6Q29tbWl0MjU4NjU3NDY0OmZmNTQ2Y2Q2MzIzMGFiOGRkZjdjYmQ2OTkzZTAwMTc2NTM4Y2UwNDk=",
            "parents": [
                {
                    "html_url": "https://github.com/cython/cython/commit/aa8b0d9b89030c0b9ace5698ae5131c623acefa4",
                    "sha": "aa8b0d9b89030c0b9ace5698ae5131c623acefa4",
                    "url": "https://api.github.com/repos/cython/cython/commits/aa8b0d9b89030c0b9ace5698ae5131c623acefa4"
                }
            ],
            "sha": "ff546cd63230ab8ddf7cbd6993e00176538ce049",
            "url": "https://api.github.com/repos/cython/cython/commits/ff546cd63230ab8ddf7cbd6993e00176538ce049"
        },
        {
            "author": {
                "avatar_url": "https://avatars3.githubusercontent.com/u/48094549?v=4",
                "events_url": "https://api.github.com/users/xavth/events{/privacy}",
                "followers_url": "https://api.github.com/users/xavth/followers",
                "following_url": "https://api.github.com/users/xavth/following{/other_user}",
                "gists_url": "https://api.github.com/users/xavth/gists{/gist_id}",
                "gravatar_id": "",
                "html_url": "https://github.com/xavth",
                "id": 48094549,
                "login": "xavth",
                "node_id": "MDQ6VXNlcjQ4MDk0NTQ5",
                "organizations_url": "https://api.github.com/users/xavth/orgs",
                "received_events_url": "https://api.github.com/users/xavth/received_events",
                "repos_url": "https://api.github.com/users/xavth/repos",
                "site_admin": false,
                "starred_url": "https://api.github.com/users/xavth/starred{/owner}{/repo}",
                "subscriptions_url": "https://api.github.com/users/xavth/subscriptions",
                "type": "User",
                "url": "https://api.github.com/users/xavth"
            },
            "comments_url": "https://api.github.com/repos/cython/cython/commits/028af30bdd1781703a26788e0ce479b81923cdf5/comments",
            "commit": {
                "author": {
                    "date": "2020-09-23T13:25:21Z",
                    "email": "xavier.thompsonkeyl@gmail.com",
                    "name": "Xavier Thompson"
                },
                "comment_count": 0,
                "committer": {
                    "date": "2020-09-23T14:16:27Z",
                    "email": "xavier.thompsonkeyl@gmail.com",
                    "name": "Xavier Thompson"
                },
                "message": "Fix cpp iteration over simple expression depending on temporaries\n\nThe implementation of the Python-style `for ... in` loop over an\niterable cpp sequence (using begin() and end()) needs to determine\nwhether the sequence should be stored in a temporary variable or\nif it can be iterated over directly.\n\nA previous fix considers that the sequence can be accessed directly\nif `sequence.is_simple()` evaluates to True.\n\nHowever it is at least theoretically be possible for an expression\nto both be simple and to depend on temporary subexpressions. In that\ncase, because the CppIteratorNode is always a temporary, the compiler\nwill by default eagerly free the temporary subexpressions for reuse\nafter the result of the sequence has been evaluated the first time.\nThis will result in subsequent calls to `result()` returning `None`\neven though the required variables are still available and in scope\nin the generated C++ code.\n\nThis commit postpones the release of temporary subexpressions until\nthe CppIteratorNode is itself disposed-of when the sequence is\naccessed directly.",
                "tree": {
                    "sha": "256fc35badef1b9ee3640d1249c780954d7e19cd",
                    "url": "https://api.github.com/repos/cython/cython/git/trees/256fc35badef1b9ee3640d1249c780954d7e19cd"
                },
                "url": "https://api.github.com/repos/cython/cython/git/commits/028af30bdd1781703a26788e0ce479b81923cdf5",
                "verification": {
                    "payload": null,
                    "reason": "unsigned",
                    "signature": null,
                    "verified": false
                }
            },
            "committer": {
                "avatar_url": "https://avatars3.githubusercontent.com/u/48094549?v=4",
                "events_url": "https://api.github.com/users/xavth/events{/privacy}",
                "followers_url": "https://api.github.com/users/xavth/followers",
                "following_url": "https://api.github.com/users/xavth/following{/other_user}",
                "gists_url": "https://api.github.com/users/xavth/gists{/gist_id}",
                "gravatar_id": "",
                "html_url": "https://github.com/xavth",
                "id": 48094549,
                "login": "xavth",
                "node_id": "MDQ6VXNlcjQ4MDk0NTQ5",
                "organizations_url": "https://api.github.com/users/xavth/orgs",
                "received_events_url": "https://api.github.com/users/xavth/received_events",
                "repos_url": "https://api.github.com/users/xavth/repos",
                "site_admin": false,
                "starred_url": "https://api.github.com/users/xavth/starred{/owner}{/repo}",
                "subscriptions_url": "https://api.github.com/users/xavth/subscriptions",
                "type": "User",
                "url": "https://api.github.com/users/xavth"
            },
            "html_url": "https://github.com/cython/cython/commit/028af30bdd1781703a26788e0ce479b81923cdf5",
            "node_id": "MDY6Q29tbWl0MjU4NjU3NDY0OjAyOGFmMzBiZGQxNzgxNzAzYTI2Nzg4ZTBjZTQ3OWI4MTkyM2NkZjU=",
            "parents": [
                {
                    "html_url": "https://github.com/cython/cython/commit/ff546cd63230ab8ddf7cbd6993e00176538ce049",
                    "sha": "ff546cd63230ab8ddf7cbd6993e00176538ce049",
                    "url": "https://api.github.com/repos/cython/cython/commits/ff546cd63230ab8ddf7cbd6993e00176538ce049"
                }
            ],
            "sha": "028af30bdd1781703a26788e0ce479b81923cdf5",
            "url": "https://api.github.com/repos/cython/cython/commits/028af30bdd1781703a26788e0ce479b81923cdf5"
        }
    ],
    "commits_url": "https://api.github.com/repos/cython/cython/pulls/3828/commits",
    "created_at": "2020-09-14T15:07:45Z",
    "diff_url": "https://github.com/cython/cython/pull/3828.diff",
    "draft": false,
    "head": {
        "label": "xavth:master",
        "ref": "master",
        "repo": {
            "archive_url": "https://api.github.com/repos/xavth/cython/{archive_format}{/ref}",
            "archived": false,
            "assignees_url": "https://api.github.com/repos/xavth/cython/assignees{/user}",
            "blobs_url": "https://api.github.com/repos/xavth/cython/git/blobs{/sha}",
            "branches_url": "https://api.github.com/repos/xavth/cython/branches{/branch}",
            "clone_url": "https://github.com/xavth/cython.git",
            "collaborators_url": "https://api.github.com/repos/xavth/cython/collaborators{/collaborator}",
            "comments_url": "https://api.github.com/repos/xavth/cython/comments{/number}",
            "commits_url": "https://api.github.com/repos/xavth/cython/commits{/sha}",
            "compare_url": "https://api.github.com/repos/xavth/cython/compare/{base}...{head}",
            "contents_url": "https://api.github.com/repos/xavth/cython/contents/{+path}",
            "contributors_url": "https://api.github.com/repos/xavth/cython/contributors",
            "created_at": "2020-04-25T00:55:18Z",
            "default_branch": "master",
            "deployments_url": "https://api.github.com/repos/xavth/cython/deployments",
            "description": "The most widely used Python to C compiler",
            "disabled": false,
            "downloads_url": "https://api.github.com/repos/xavth/cython/downloads",
            "events_url": "https://api.github.com/repos/xavth/cython/events",
            "fork": true,
            "forks": 0,
            "forks_count": 0,
            "forks_url": "https://api.github.com/repos/xavth/cython/forks",
            "full_name": "xavth/cython",
            "git_commits_url": "https://api.github.com/repos/xavth/cython/git/commits{/sha}",
            "git_refs_url": "https://api.github.com/repos/xavth/cython/git/refs{/sha}",
            "git_tags_url": "https://api.github.com/repos/xavth/cython/git/tags{/sha}",
            "git_url": "git://github.com/xavth/cython.git",
            "has_downloads": true,
            "has_issues": false,
            "has_pages": false,
            "has_projects": true,
            "has_wiki": true,
            "homepage": "https://cython.org",
            "hooks_url": "https://api.github.com/repos/xavth/cython/hooks",
            "html_url": "https://github.com/xavth/cython",
            "id": 258657464,
            "issue_comment_url": "https://api.github.com/repos/xavth/cython/issues/comments{/number}",
            "issue_events_url": "https://api.github.com/repos/xavth/cython/issues/events{/number}",
            "issues_url": "https://api.github.com/repos/xavth/cython/issues{/number}",
            "keys_url": "https://api.github.com/repos/xavth/cython/keys{/key_id}",
            "labels_url": "https://api.github.com/repos/xavth/cython/labels{/name}",
            "language": "Python",
            "languages_url": "https://api.github.com/repos/xavth/cython/languages",
            "license": {
                "key": "other",
                "name": "Other",
                "node_id": "MDc6TGljZW5zZTA=",
                "spdx_id": "NOASSERTION",
                "url": null
            },
            "merges_url": "https://api.github.com/repos/xavth/cython/merges",
            "milestones_url": "https://api.github.com/repos/xavth/cython/milestones{/number}",
            "mirror_url": null,
            "name": "cython",
            "node_id": "MDEwOlJlcG9zaXRvcnkyNTg2NTc0NjQ=",
            "notifications_url": "https://api.github.com/repos/xavth/cython/notifications{?since,all,participating}",
            "open_issues": 0,
            "open_issues_count": 0,
            "owner": {
                "avatar_url": "https://avatars3.githubusercontent.com/u/48094549?v=4",
                "events_url": "https://api.github.com/users/xavth/events{/privacy}",
                "followers_url": "https://api.github.com/users/xavth/followers",
                "following_url": "https://api.github.com/users/xavth/following{/other_user}",
                "gists_url": "https://api.github.com/users/xavth/gists{/gist_id}",
                "gravatar_id": "",
                "html_url": "https://github.com/xavth",
                "id": 48094549,
                "login": "xavth",
                "node_id": "MDQ6VXNlcjQ4MDk0NTQ5",
                "organizations_url": "https://api.github.com/users/xavth/orgs",
                "received_events_url": "https://api.github.com/users/xavth/received_events",
                "repos_url": "https://api.github.com/users/xavth/repos",
                "site_admin": false,
                "starred_url": "https://api.github.com/users/xavth/starred{/owner}{/repo}",
                "subscriptions_url": "https://api.github.com/users/xavth/subscriptions",
                "type": "User",
                "url": "https://api.github.com/users/xavth"
            },
            "private": false,
            "pulls_url": "https://api.github.com/repos/xavth/cython/pulls{/number}",
            "pushed_at": "2020-09-23T15:33:48Z",
            "releases_url": "https://api.github.com/repos/xavth/cython/releases{/id}",
            "size": 59987,
            "ssh_url": "git@github.com:xavth/cython.git",
            "stargazers_count": 0,
            "stargazers_url": "https://api.github.com/repos/xavth/cython/stargazers",
            "statuses_url": "https://api.github.com/repos/xavth/cython/statuses/{sha}",
            "subscribers_url": "https://api.github.com/repos/xavth/cython/subscribers",
            "subscription_url": "https://api.github.com/repos/xavth/cython/subscription",
            "svn_url": "https://github.com/xavth/cython",
            "tags_url": "https://api.github.com/repos/xavth/cython/tags",
            "teams_url": "https://api.github.com/repos/xavth/cython/teams",
            "trees_url": "https://api.github.com/repos/xavth/cython/git/trees{/sha}",
            "updated_at": "2020-09-23T15:33:53Z",
            "url": "https://api.github.com/repos/xavth/cython",
            "watchers": 0,
            "watchers_count": 0
        },
        "sha": "028af30bdd1781703a26788e0ce479b81923cdf5",
        "user": {
            "avatar_url": "https://avatars3.githubusercontent.com/u/48094549?v=4",
            "events_url": "https://api.github.com/users/xavth/events{/privacy}",
            "followers_url": "https://api.github.com/users/xavth/followers",
            "following_url": "https://api.github.com/users/xavth/following{/other_user}",
            "gists_url": "https://api.github.com/users/xavth/gists{/gist_id}",
            "gravatar_id": "",
            "html_url": "https://github.com/xavth",
            "id": 48094549,
            "login": "xavth",
            "node_id": "MDQ6VXNlcjQ4MDk0NTQ5",
            "organizations_url": "https://api.github.com/users/xavth/orgs",
            "received_events_url": "https://api.github.com/users/xavth/received_events",
            "repos_url": "https://api.github.com/users/xavth/repos",
            "site_admin": false,
            "starred_url": "https://api.github.com/users/xavth/starred{/owner}{/repo}",
            "subscriptions_url": "https://api.github.com/users/xavth/subscriptions",
            "type": "User",
            "url": "https://api.github.com/users/xavth"
        }
    },
    "html_url": "https://github.com/cython/cython/pull/3828",
    "id": 486688957,
    "issue_url": "https://api.github.com/repos/cython/cython/issues/3828",
    "labels": [],
    "locked": false,
    "merge_commit_sha": "0c128b65cc949ba8de027b3a6e0ac8dac2878141",
    "merged_at": null,
    "milestone": null,
    "node_id": "MDExOlB1bGxSZXF1ZXN0NDg2Njg4OTU3",
    "number": 3828,
    "patch_url": "https://github.com/cython/cython/pull/3828.patch",
    "requested_reviewers": [],
    "requested_teams": [],
    "review_comment_url": "https://api.github.com/repos/cython/cython/pulls/comments{/number}",
    "review_comments_url": "https://api.github.com/repos/cython/cython/pulls/3828/comments",
    "state": "open",
    "statuses_url": "https://api.github.com/repos/cython/cython/statuses/028af30bdd1781703a26788e0ce479b81923cdf5",
    "title": "Fix bug in cpp iteration over rvalue-dependant attribute",
    "updated_at": "2020-09-23T15:33:51Z",
    "url": "https://api.github.com/repos/cython/cython/pulls/3828",
    "user": {
        "avatar_url": "https://avatars3.githubusercontent.com/u/48094549?v=4",
        "events_url": "https://api.github.com/users/xavth/events{/privacy}",
        "followers_url": "https://api.github.com/users/xavth/followers",
        "following_url": "https://api.github.com/users/xavth/following{/other_user}",
        "gists_url": "https://api.github.com/users/xavth/gists{/gist_id}",
        "gravatar_id": "",
        "html_url": "https://github.com/xavth",
        "id": 48094549,
        "login": "xavth",
        "node_id": "MDQ6VXNlcjQ4MDk0NTQ5",
        "organizations_url": "https://api.github.com/users/xavth/orgs",
        "received_events_url": "https://api.github.com/users/xavth/received_events",
        "repos_url": "https://api.github.com/users/xavth/repos",
        "site_admin": false,
        "starred_url": "https://api.github.com/users/xavth/starred{/owner}{/repo}",
        "subscriptions_url": "https://api.github.com/users/xavth/subscriptions",
        "type": "User",
        "url": "https://api.github.com/users/xavth"
    }
}