{
    "_links": {
        "comments": {
            "href": "https://api.github.com/repos/cython/cython/issues/6917/comments"
        },
        "commits": {
            "href": "https://api.github.com/repos/cython/cython/pulls/6917/commits"
        },
        "html": {
            "href": "https://github.com/cython/cython/pull/6917"
        },
        "issue": {
            "href": "https://api.github.com/repos/cython/cython/issues/6917"
        },
        "review_comment": {
            "href": "https://api.github.com/repos/cython/cython/pulls/comments{/number}"
        },
        "review_comments": {
            "href": "https://api.github.com/repos/cython/cython/pulls/6917/comments"
        },
        "self": {
            "href": "https://api.github.com/repos/cython/cython/pulls/6917"
        },
        "statuses": {
            "href": "https://api.github.com/repos/cython/cython/statuses/e23bfcbfa31c9bb467535f5b62f8dc0d22454419"
        }
    },
    "active_lock_reason": null,
    "assignee": null,
    "assignees": [],
    "author_association": "MEMBER",
    "auto_merge": {
        "commit_message": "I don't propose using this on the CI (there's just too many combinations\nto test) but I think it's a useful thing to be able to do locally.",
        "commit_title": "Add an option to runtests to run with a specific Limited API version (#6917)",
        "enabled_by": {
            "avatar_url": "https://avatars.githubusercontent.com/u/10536947?v=4",
            "events_url": "https://api.github.com/users/da-woods/events{/privacy}",
            "followers_url": "https://api.github.com/users/da-woods/followers",
            "following_url": "https://api.github.com/users/da-woods/following{/other_user}",
            "gists_url": "https://api.github.com/users/da-woods/gists{/gist_id}",
            "gravatar_id": "",
            "html_url": "https://github.com/da-woods",
            "id": 10536947,
            "login": "da-woods",
            "node_id": "MDQ6VXNlcjEwNTM2OTQ3",
            "organizations_url": "https://api.github.com/users/da-woods/orgs",
            "received_events_url": "https://api.github.com/users/da-woods/received_events",
            "repos_url": "https://api.github.com/users/da-woods/repos",
            "site_admin": false,
            "starred_url": "https://api.github.com/users/da-woods/starred{/owner}{/repo}",
            "subscriptions_url": "https://api.github.com/users/da-woods/subscriptions",
            "type": "User",
            "url": "https://api.github.com/users/da-woods",
            "user_view_type": "public"
        },
        "merge_method": "squash"
    },
    "base": {
        "label": "cython:master",
        "ref": "master",
        "repo": {
            "allow_forking": true,
            "archive_url": "https://api.github.com/repos/cython/cython/{archive_format}{/ref}",
            "archived": false,
            "assignees_url": "https://api.github.com/repos/cython/cython/assignees{/user}",
            "blobs_url": "https://api.github.com/repos/cython/cython/git/blobs{/sha}",
            "branches_url": "https://api.github.com/repos/cython/cython/branches{/branch}",
            "clone_url": "https://github.com/cython/cython.git",
            "collaborators_url": "https://api.github.com/repos/cython/cython/collaborators{/collaborator}",
            "comments_url": "https://api.github.com/repos/cython/cython/comments{/number}",
            "commits_url": "https://api.github.com/repos/cython/cython/commits{/sha}",
            "compare_url": "https://api.github.com/repos/cython/cython/compare/{base}...{head}",
            "contents_url": "https://api.github.com/repos/cython/cython/contents/{+path}",
            "contributors_url": "https://api.github.com/repos/cython/cython/contributors",
            "created_at": "2010-11-21T07:44:20Z",
            "default_branch": "master",
            "deployments_url": "https://api.github.com/repos/cython/cython/deployments",
            "description": "The most widely used Python to C compiler",
            "disabled": false,
            "downloads_url": "https://api.github.com/repos/cython/cython/downloads",
            "events_url": "https://api.github.com/repos/cython/cython/events",
            "fork": false,
            "forks": 1528,
            "forks_count": 1528,
            "forks_url": "https://api.github.com/repos/cython/cython/forks",
            "full_name": "cython/cython",
            "git_commits_url": "https://api.github.com/repos/cython/cython/git/commits{/sha}",
            "git_refs_url": "https://api.github.com/repos/cython/cython/git/refs{/sha}",
            "git_tags_url": "https://api.github.com/repos/cython/cython/git/tags{/sha}",
            "git_url": "git://github.com/cython/cython.git",
            "has_discussions": false,
            "has_downloads": true,
            "has_issues": true,
            "has_pages": false,
            "has_projects": false,
            "has_wiki": true,
            "homepage": "https://cython.org",
            "hooks_url": "https://api.github.com/repos/cython/cython/hooks",
            "html_url": "https://github.com/cython/cython",
            "id": 1099265,
            "is_template": false,
            "issue_comment_url": "https://api.github.com/repos/cython/cython/issues/comments{/number}",
            "issue_events_url": "https://api.github.com/repos/cython/cython/issues/events{/number}",
            "issues_url": "https://api.github.com/repos/cython/cython/issues{/number}",
            "keys_url": "https://api.github.com/repos/cython/cython/keys{/key_id}",
            "labels_url": "https://api.github.com/repos/cython/cython/labels{/name}",
            "language": "Python",
            "languages_url": "https://api.github.com/repos/cython/cython/languages",
            "license": {
                "key": "apache-2.0",
                "name": "Apache License 2.0",
                "node_id": "MDc6TGljZW5zZTI=",
                "spdx_id": "Apache-2.0",
                "url": "https://api.github.com/licenses/apache-2.0"
            },
            "merges_url": "https://api.github.com/repos/cython/cython/merges",
            "milestones_url": "https://api.github.com/repos/cython/cython/milestones{/number}",
            "mirror_url": null,
            "name": "cython",
            "node_id": "MDEwOlJlcG9zaXRvcnkxMDk5MjY1",
            "notifications_url": "https://api.github.com/repos/cython/cython/notifications{?since,all,participating}",
            "open_issues": 1441,
            "open_issues_count": 1441,
            "owner": {
                "avatar_url": "https://avatars.githubusercontent.com/u/486082?v=4",
                "events_url": "https://api.github.com/users/cython/events{/privacy}",
                "followers_url": "https://api.github.com/users/cython/followers",
                "following_url": "https://api.github.com/users/cython/following{/other_user}",
                "gists_url": "https://api.github.com/users/cython/gists{/gist_id}",
                "gravatar_id": "",
                "html_url": "https://github.com/cython",
                "id": 486082,
                "login": "cython",
                "node_id": "MDEyOk9yZ2FuaXphdGlvbjQ4NjA4Mg==",
                "organizations_url": "https://api.github.com/users/cython/orgs",
                "received_events_url": "https://api.github.com/users/cython/received_events",
                "repos_url": "https://api.github.com/users/cython/repos",
                "site_admin": false,
                "starred_url": "https://api.github.com/users/cython/starred{/owner}{/repo}",
                "subscriptions_url": "https://api.github.com/users/cython/subscriptions",
                "type": "Organization",
                "url": "https://api.github.com/users/cython",
                "user_view_type": "public"
            },
            "private": false,
            "pulls_url": "https://api.github.com/repos/cython/cython/pulls{/number}",
            "pushed_at": "2025-05-27T09:04:51Z",
            "releases_url": "https://api.github.com/repos/cython/cython/releases{/id}",
            "size": 75896,
            "ssh_url": "git@github.com:cython/cython.git",
            "stargazers_count": 10023,
            "stargazers_url": "https://api.github.com/repos/cython/cython/stargazers",
            "statuses_url": "https://api.github.com/repos/cython/cython/statuses/{sha}",
            "subscribers_url": "https://api.github.com/repos/cython/cython/subscribers",
            "subscription_url": "https://api.github.com/repos/cython/cython/subscription",
            "svn_url": "https://github.com/cython/cython",
            "tags_url": "https://api.github.com/repos/cython/cython/tags",
            "teams_url": "https://api.github.com/repos/cython/cython/teams",
            "topics": [
                "big-data",
                "c",
                "cpp",
                "cpython",
                "cpython-extensions",
                "cython",
                "performance",
                "python"
            ],
            "trees_url": "https://api.github.com/repos/cython/cython/git/trees{/sha}",
            "updated_at": "2025-05-27T09:04:56Z",
            "url": "https://api.github.com/repos/cython/cython",
            "visibility": "public",
            "watchers": 10023,
            "watchers_count": 10023,
            "web_commit_signoff_required": false
        },
        "sha": "a2e5e3986b333756e7bdebcd3a8ae5b0dccefc93",
        "user": {
            "avatar_url": "https://avatars.githubusercontent.com/u/486082?v=4",
            "events_url": "https://api.github.com/users/cython/events{/privacy}",
            "followers_url": "https://api.github.com/users/cython/followers",
            "following_url": "https://api.github.com/users/cython/following{/other_user}",
            "gists_url": "https://api.github.com/users/cython/gists{/gist_id}",
            "gravatar_id": "",
            "html_url": "https://github.com/cython",
            "id": 486082,
            "login": "cython",
            "node_id": "MDEyOk9yZ2FuaXphdGlvbjQ4NjA4Mg==",
            "organizations_url": "https://api.github.com/users/cython/orgs",
            "received_events_url": "https://api.github.com/users/cython/received_events",
            "repos_url": "https://api.github.com/users/cython/repos",
            "site_admin": false,
            "starred_url": "https://api.github.com/users/cython/starred{/owner}{/repo}",
            "subscriptions_url": "https://api.github.com/users/cython/subscriptions",
            "type": "Organization",
            "url": "https://api.github.com/users/cython",
            "user_view_type": "public"
        }
    },
    "body": "I don't propose using this on the CI (there's just too many combinations to test) but I think it's a useful thing to be able to do locally.",
    "closed_at": "2025-05-26T22:02:55Z",
    "comment_data": [
        {
            "_links": {
                "html": {
                    "href": "https://github.com/cython/cython/pull/6917#discussion_r2107796682"
                },
                "pull_request": {
                    "href": "https://api.github.com/repos/cython/cython/pulls/6917"
                },
                "self": {
                    "href": "https://api.github.com/repos/cython/cython/pulls/comments/2107796682"
                }
            },
            "author_association": "MEMBER",
            "body": "```suggestion\r\n        help=(\"Use CPython's Limited API. \"\r\n              \"Accepts an optional API version in the form '3.11', otherwise uses current.\"))\r\n```",
            "commit_id": "e23bfcbfa31c9bb467535f5b62f8dc0d22454419",
            "created_at": "2025-05-26T19:40:05Z",
            "diff_hunk": "@@ -2447,8 +2449,8 @@ def main():\n         \"--no-capture\", dest=\"capture\", default=True, action=\"store_false\",\n         help=\"do not capture stdout, stderr in srctree tests. Makes pdb.set_trace interactive\")\n     parser.add_argument(\n-        \"--limited-api\", dest=\"limited_api\", default=False, action=\"store_true\",\n-        help=\"Compiles Cython using CPython's LIMITED_API\")\n+        \"--limited-api\", dest=\"limited_api\", nargs='?', default=False, const=True, action=\"store\",\n+        help=\"Compiles Cython using CPython's LIMITED_API. You can optional specify a version in the form '3.11'\")",
            "html_url": "https://github.com/cython/cython/pull/6917#discussion_r2107796682",
            "id": 2107796682,
            "line": null,
            "node_id": "PRRC_kwDOABDGAc59omzK",
            "original_commit_id": "9cec077741b567109aeff3f94a15a107d776364e",
            "original_line": 2453,
            "original_position": 18,
            "original_start_line": null,
            "path": "runtests.py",
            "position": null,
            "pull_request_review_id": 2869083381,
            "pull_request_url": "https://api.github.com/repos/cython/cython/pulls/6917",
            "reactions": {
                "+1": 0,
                "-1": 0,
                "confused": 0,
                "eyes": 0,
                "heart": 0,
                "hooray": 0,
                "laugh": 0,
                "rocket": 0,
                "total_count": 0,
                "url": "https://api.github.com/repos/cython/cython/pulls/comments/2107796682/reactions"
            },
            "side": "RIGHT",
            "start_line": null,
            "start_side": null,
            "subject_type": "line",
            "updated_at": "2025-05-26T19:53:04Z",
            "url": "https://api.github.com/repos/cython/cython/pulls/comments/2107796682",
            "user": {
                "avatar_url": "https://avatars.githubusercontent.com/u/491659?v=4",
                "events_url": "https://api.github.com/users/scoder/events{/privacy}",
                "followers_url": "https://api.github.com/users/scoder/followers",
                "following_url": "https://api.github.com/users/scoder/following{/other_user}",
                "gists_url": "https://api.github.com/users/scoder/gists{/gist_id}",
                "gravatar_id": "",
                "html_url": "https://github.com/scoder",
                "id": 491659,
                "login": "scoder",
                "node_id": "MDQ6VXNlcjQ5MTY1OQ==",
                "organizations_url": "https://api.github.com/users/scoder/orgs",
                "received_events_url": "https://api.github.com/users/scoder/received_events",
                "repos_url": "https://api.github.com/users/scoder/repos",
                "site_admin": false,
                "starred_url": "https://api.github.com/users/scoder/starred{/owner}{/repo}",
                "subscriptions_url": "https://api.github.com/users/scoder/subscriptions",
                "type": "User",
                "url": "https://api.github.com/users/scoder",
                "user_view_type": "public"
            }
        },
        {
            "_links": {
                "html": {
                    "href": "https://github.com/cython/cython/pull/6917#discussion_r2107800759"
                },
                "pull_request": {
                    "href": "https://api.github.com/repos/cython/cython/pulls/6917"
                },
                "self": {
                    "href": "https://api.github.com/repos/cython/cython/pulls/comments/2107800759"
                }
            },
            "author_association": "MEMBER",
            "body": "```suggestion\r\n        \"--limited-api\", dest=\"limited_api\", nargs='?', default='', const=\"%d.%d\" % sys.version_info[:2], action=\"store\",\r\n```",
            "commit_id": "e23bfcbfa31c9bb467535f5b62f8dc0d22454419",
            "created_at": "2025-05-26T19:46:28Z",
            "diff_hunk": "@@ -2447,8 +2449,8 @@ def main():\n         \"--no-capture\", dest=\"capture\", default=True, action=\"store_false\",\n         help=\"do not capture stdout, stderr in srctree tests. Makes pdb.set_trace interactive\")\n     parser.add_argument(\n-        \"--limited-api\", dest=\"limited_api\", default=False, action=\"store_true\",\n-        help=\"Compiles Cython using CPython's LIMITED_API\")\n+        \"--limited-api\", dest=\"limited_api\", nargs='?', default=False, const=True, action=\"store\",",
            "html_url": "https://github.com/cython/cython/pull/6917#discussion_r2107800759",
            "id": 2107800759,
            "line": null,
            "node_id": "PRRC_kwDOABDGAc59ony3",
            "original_commit_id": "9cec077741b567109aeff3f94a15a107d776364e",
            "original_line": 2452,
            "original_position": 17,
            "original_start_line": null,
            "path": "runtests.py",
            "position": null,
            "pull_request_review_id": 2869083381,
            "pull_request_url": "https://api.github.com/repos/cython/cython/pulls/6917",
            "reactions": {
                "+1": 0,
                "-1": 0,
                "confused": 0,
                "eyes": 0,
                "heart": 0,
                "hooray": 0,
                "laugh": 0,
                "rocket": 0,
                "total_count": 0,
                "url": "https://api.github.com/repos/cython/cython/pulls/comments/2107800759/reactions"
            },
            "side": "RIGHT",
            "start_line": null,
            "start_side": null,
            "subject_type": "line",
            "updated_at": "2025-05-26T19:51:45Z",
            "url": "https://api.github.com/repos/cython/cython/pulls/comments/2107800759",
            "user": {
                "avatar_url": "https://avatars.githubusercontent.com/u/491659?v=4",
                "events_url": "https://api.github.com/users/scoder/events{/privacy}",
                "followers_url": "https://api.github.com/users/scoder/followers",
                "following_url": "https://api.github.com/users/scoder/following{/other_user}",
                "gists_url": "https://api.github.com/users/scoder/gists{/gist_id}",
                "gravatar_id": "",
                "html_url": "https://github.com/scoder",
                "id": 491659,
                "login": "scoder",
                "node_id": "MDQ6VXNlcjQ5MTY1OQ==",
                "organizations_url": "https://api.github.com/users/scoder/orgs",
                "received_events_url": "https://api.github.com/users/scoder/received_events",
                "repos_url": "https://api.github.com/users/scoder/repos",
                "site_admin": false,
                "starred_url": "https://api.github.com/users/scoder/starred{/owner}{/repo}",
                "subscriptions_url": "https://api.github.com/users/scoder/subscriptions",
                "type": "User",
                "url": "https://api.github.com/users/scoder",
                "user_view_type": "public"
            }
        },
        {
            "_links": {
                "html": {
                    "href": "https://github.com/cython/cython/pull/6917#discussion_r2107802115"
                },
                "pull_request": {
                    "href": "https://api.github.com/repos/cython/cython/pulls/6917"
                },
                "self": {
                    "href": "https://api.github.com/repos/cython/cython/pulls/comments/2107802115"
                }
            },
            "author_association": "MEMBER",
            "body": "We do not support running the test runner in a different Python version than the tests (and I don't see a real incentive to implement that), so this seems a useless special case. Let's remove it and always generate the version string from the option value.",
            "commit_id": "e23bfcbfa31c9bb467535f5b62f8dc0d22454419",
            "created_at": "2025-05-26T19:48:36Z",
            "diff_hunk": "@@ -2733,9 +2735,26 @@ def runtests(options, cmd_args, coverage=None):\n             refnanny = import_refnanny()\n         CDEFS.append(('CYTHON_REFNANNY', '1'))\n \n+    sys_version_or_limited_version = sys.version_info\n     if options.limited_api:\n-        CDEFS.append(('CYTHON_LIMITED_API', '1'))\n-        CDEFS.append((\"Py_LIMITED_API\", '(PY_VERSION_HEX & 0xffff0000)'))\n+        if options.limited_api is True:\n+            CDEFS.append((\"Py_LIMITED_API\", '(PY_VERSION_HEX & 0xffff0000)'))\n+        else:",
            "html_url": "https://github.com/cython/cython/pull/6917#discussion_r2107802115",
            "id": 2107802115,
            "line": null,
            "node_id": "PRRC_kwDOABDGAc59ooID",
            "original_commit_id": "9cec077741b567109aeff3f94a15a107d776364e",
            "original_line": 2742,
            "original_position": 32,
            "original_start_line": 2737,
            "path": "runtests.py",
            "position": null,
            "pull_request_review_id": 2869083381,
            "pull_request_url": "https://api.github.com/repos/cython/cython/pulls/6917",
            "reactions": {
                "+1": 0,
                "-1": 0,
                "confused": 0,
                "eyes": 0,
                "heart": 0,
                "hooray": 0,
                "laugh": 0,
                "rocket": 0,
                "total_count": 0,
                "url": "https://api.github.com/repos/cython/cython/pulls/comments/2107802115/reactions"
            },
            "side": "RIGHT",
            "start_line": null,
            "start_side": "LEFT",
            "subject_type": "line",
            "updated_at": "2025-05-26T19:51:45Z",
            "url": "https://api.github.com/repos/cython/cython/pulls/comments/2107802115",
            "user": {
                "avatar_url": "https://avatars.githubusercontent.com/u/491659?v=4",
                "events_url": "https://api.github.com/users/scoder/events{/privacy}",
                "followers_url": "https://api.github.com/users/scoder/followers",
                "following_url": "https://api.github.com/users/scoder/following{/other_user}",
                "gists_url": "https://api.github.com/users/scoder/gists{/gist_id}",
                "gravatar_id": "",
                "html_url": "https://github.com/scoder",
                "id": 491659,
                "login": "scoder",
                "node_id": "MDQ6VXNlcjQ5MTY1OQ==",
                "organizations_url": "https://api.github.com/users/scoder/orgs",
                "received_events_url": "https://api.github.com/users/scoder/received_events",
                "repos_url": "https://api.github.com/users/scoder/repos",
                "site_admin": false,
                "starred_url": "https://api.github.com/users/scoder/starred{/owner}{/repo}",
                "subscriptions_url": "https://api.github.com/users/scoder/subscriptions",
                "type": "User",
                "url": "https://api.github.com/users/scoder",
                "user_view_type": "public"
            }
        }
    ],
    "comments_url": "https://api.github.com/repos/cython/cython/issues/6917/comments",
    "commit_data": [
        {
            "author": {
                "avatar_url": "https://avatars.githubusercontent.com/u/10536947?v=4",
                "events_url": "https://api.github.com/users/da-woods/events{/privacy}",
                "followers_url": "https://api.github.com/users/da-woods/followers",
                "following_url": "https://api.github.com/users/da-woods/following{/other_user}",
                "gists_url": "https://api.github.com/users/da-woods/gists{/gist_id}",
                "gravatar_id": "",
                "html_url": "https://github.com/da-woods",
                "id": 10536947,
                "login": "da-woods",
                "node_id": "MDQ6VXNlcjEwNTM2OTQ3",
                "organizations_url": "https://api.github.com/users/da-woods/orgs",
                "received_events_url": "https://api.github.com/users/da-woods/received_events",
                "repos_url": "https://api.github.com/users/da-woods/repos",
                "site_admin": false,
                "starred_url": "https://api.github.com/users/da-woods/starred{/owner}{/repo}",
                "subscriptions_url": "https://api.github.com/users/da-woods/subscriptions",
                "type": "User",
                "url": "https://api.github.com/users/da-woods",
                "user_view_type": "public"
            },
            "comments_url": "https://api.github.com/repos/cython/cython/commits/90c203aa725b121310b5d0d07c31ced5209a6d89/comments",
            "commit": {
                "author": {
                    "date": "2025-05-26T13:57:02Z",
                    "email": "dw-git@d-woods.co.uk",
                    "name": "da-woods"
                },
                "comment_count": 0,
                "committer": {
                    "date": "2025-05-26T13:57:02Z",
                    "email": "dw-git@d-woods.co.uk",
                    "name": "da-woods"
                },
                "message": "Add an option to runtests to run with a specific Limited API version\n\nI don't propose using this on the CI (there's just too many\ncombinations to test) but I think it's a useful thing to be\nable to do locally.",
                "tree": {
                    "sha": "8c80182241ee6e936fcf14a490eeafee9b6aa6f3",
                    "url": "https://api.github.com/repos/cython/cython/git/trees/8c80182241ee6e936fcf14a490eeafee9b6aa6f3"
                },
                "url": "https://api.github.com/repos/cython/cython/git/commits/90c203aa725b121310b5d0d07c31ced5209a6d89",
                "verification": {
                    "payload": null,
                    "reason": "unsigned",
                    "signature": null,
                    "verified": false,
                    "verified_at": null
                }
            },
            "committer": {
                "avatar_url": "https://avatars.githubusercontent.com/u/10536947?v=4",
                "events_url": "https://api.github.com/users/da-woods/events{/privacy}",
                "followers_url": "https://api.github.com/users/da-woods/followers",
                "following_url": "https://api.github.com/users/da-woods/following{/other_user}",
                "gists_url": "https://api.github.com/users/da-woods/gists{/gist_id}",
                "gravatar_id": "",
                "html_url": "https://github.com/da-woods",
                "id": 10536947,
                "login": "da-woods",
                "node_id": "MDQ6VXNlcjEwNTM2OTQ3",
                "organizations_url": "https://api.github.com/users/da-woods/orgs",
                "received_events_url": "https://api.github.com/users/da-woods/received_events",
                "repos_url": "https://api.github.com/users/da-woods/repos",
                "site_admin": false,
                "starred_url": "https://api.github.com/users/da-woods/starred{/owner}{/repo}",
                "subscriptions_url": "https://api.github.com/users/da-woods/subscriptions",
                "type": "User",
                "url": "https://api.github.com/users/da-woods",
                "user_view_type": "public"
            },
            "html_url": "https://github.com/cython/cython/commit/90c203aa725b121310b5d0d07c31ced5209a6d89",
            "node_id": "C_kwDOAhr4b9oAKDkwYzIwM2FhNzI1YjEyMTMxMGI1ZDBkMDdjMzFjZWQ1MjA5YTZkODk",
            "parents": [
                {
                    "html_url": "https://github.com/cython/cython/commit/1775c9c6ff0d7f22b0d2dc9c37d77c3571e8e4b6",
                    "sha": "1775c9c6ff0d7f22b0d2dc9c37d77c3571e8e4b6",
                    "url": "https://api.github.com/repos/cython/cython/commits/1775c9c6ff0d7f22b0d2dc9c37d77c3571e8e4b6"
                }
            ],
            "sha": "90c203aa725b121310b5d0d07c31ced5209a6d89",
            "url": "https://api.github.com/repos/cython/cython/commits/90c203aa725b121310b5d0d07c31ced5209a6d89"
        },
        {
            "author": {
                "avatar_url": "https://avatars.githubusercontent.com/u/10536947?v=4",
                "events_url": "https://api.github.com/users/da-woods/events{/privacy}",
                "followers_url": "https://api.github.com/users/da-woods/followers",
                "following_url": "https://api.github.com/users/da-woods/following{/other_user}",
                "gists_url": "https://api.github.com/users/da-woods/gists{/gist_id}",
                "gravatar_id": "",
                "html_url": "https://github.com/da-woods",
                "id": 10536947,
                "login": "da-woods",
                "node_id": "MDQ6VXNlcjEwNTM2OTQ3",
                "organizations_url": "https://api.github.com/users/da-woods/orgs",
                "received_events_url": "https://api.github.com/users/da-woods/received_events",
                "repos_url": "https://api.github.com/users/da-woods/repos",
                "site_admin": false,
                "starred_url": "https://api.github.com/users/da-woods/starred{/owner}{/repo}",
                "subscriptions_url": "https://api.github.com/users/da-woods/subscriptions",
                "type": "User",
                "url": "https://api.github.com/users/da-woods",
                "user_view_type": "public"
            },
            "comments_url": "https://api.github.com/repos/cython/cython/commits/66e708a464643385413e0ca9e94a15884e04bd84/comments",
            "commit": {
                "author": {
                    "date": "2025-05-26T15:38:31Z",
                    "email": "dw-git@d-woods.co.uk",
                    "name": "da-woods"
                },
                "comment_count": 0,
                "committer": {
                    "date": "2025-05-26T15:38:31Z",
                    "email": "dw-git@d-woods.co.uk",
                    "name": "da-woods"
                },
                "message": "Merge remote-tracking branch 'real_origin/master' into pick-limited-api-version-to-test",
                "tree": {
                    "sha": "e32d05cfb8c78894e05bc5489843db468264283e",
                    "url": "https://api.github.com/repos/cython/cython/git/trees/e32d05cfb8c78894e05bc5489843db468264283e"
                },
                "url": "https://api.github.com/repos/cython/cython/git/commits/66e708a464643385413e0ca9e94a15884e04bd84",
                "verification": {
                    "payload": null,
                    "reason": "unsigned",
                    "signature": null,
                    "verified": false,
                    "verified_at": null
                }
            },
            "committer": {
                "avatar_url": "https://avatars.githubusercontent.com/u/10536947?v=4",
                "events_url": "https://api.github.com/users/da-woods/events{/privacy}",
                "followers_url": "https://api.github.com/users/da-woods/followers",
                "following_url": "https://api.github.com/users/da-woods/following{/other_user}",
                "gists_url": "https://api.github.com/users/da-woods/gists{/gist_id}",
                "gravatar_id": "",
                "html_url": "https://github.com/da-woods",
                "id": 10536947,
                "login": "da-woods",
                "node_id": "MDQ6VXNlcjEwNTM2OTQ3",
                "organizations_url": "https://api.github.com/users/da-woods/orgs",
                "received_events_url": "https://api.github.com/users/da-woods/received_events",
                "repos_url": "https://api.github.com/users/da-woods/repos",
                "site_admin": false,
                "starred_url": "https://api.github.com/users/da-woods/starred{/owner}{/repo}",
                "subscriptions_url": "https://api.github.com/users/da-woods/subscriptions",
                "type": "User",
                "url": "https://api.github.com/users/da-woods",
                "user_view_type": "public"
            },
            "html_url": "https://github.com/cython/cython/commit/66e708a464643385413e0ca9e94a15884e04bd84",
            "node_id": "C_kwDOAhr4b9oAKDY2ZTcwOGE0NjQ2NDMzODU0MTNlMGNhOWU5NGExNTg4NGUwNGJkODQ",
            "parents": [
                {
                    "html_url": "https://github.com/cython/cython/commit/90c203aa725b121310b5d0d07c31ced5209a6d89",
                    "sha": "90c203aa725b121310b5d0d07c31ced5209a6d89",
                    "url": "https://api.github.com/repos/cython/cython/commits/90c203aa725b121310b5d0d07c31ced5209a6d89"
                },
                {
                    "html_url": "https://github.com/cython/cython/commit/a2e5e3986b333756e7bdebcd3a8ae5b0dccefc93",
                    "sha": "a2e5e3986b333756e7bdebcd3a8ae5b0dccefc93",
                    "url": "https://api.github.com/repos/cython/cython/commits/a2e5e3986b333756e7bdebcd3a8ae5b0dccefc93"
                }
            ],
            "sha": "66e708a464643385413e0ca9e94a15884e04bd84",
            "url": "https://api.github.com/repos/cython/cython/commits/66e708a464643385413e0ca9e94a15884e04bd84"
        },
        {
            "author": {
                "avatar_url": "https://avatars.githubusercontent.com/u/10536947?v=4",
                "events_url": "https://api.github.com/users/da-woods/events{/privacy}",
                "followers_url": "https://api.github.com/users/da-woods/followers",
                "following_url": "https://api.github.com/users/da-woods/following{/other_user}",
                "gists_url": "https://api.github.com/users/da-woods/gists{/gist_id}",
                "gravatar_id": "",
                "html_url": "https://github.com/da-woods",
                "id": 10536947,
                "login": "da-woods",
                "node_id": "MDQ6VXNlcjEwNTM2OTQ3",
                "organizations_url": "https://api.github.com/users/da-woods/orgs",
                "received_events_url": "https://api.github.com/users/da-woods/received_events",
                "repos_url": "https://api.github.com/users/da-woods/repos",
                "site_admin": false,
                "starred_url": "https://api.github.com/users/da-woods/starred{/owner}{/repo}",
                "subscriptions_url": "https://api.github.com/users/da-woods/subscriptions",
                "type": "User",
                "url": "https://api.github.com/users/da-woods",
                "user_view_type": "public"
            },
            "comments_url": "https://api.github.com/repos/cython/cython/commits/491434fff8477e1a76926515600c45e45329c30c/comments",
            "commit": {
                "author": {
                    "date": "2025-05-26T15:40:13Z",
                    "email": "dw-git@d-woods.co.uk",
                    "name": "da-woods"
                },
                "comment_count": 0,
                "committer": {
                    "date": "2025-05-26T15:40:13Z",
                    "email": "dw-git@d-woods.co.uk",
                    "name": "da-woods"
                },
                "message": "Add back in documentation of forrmat",
                "tree": {
                    "sha": "e2a275d5adb4d4afa28d6987b364bb244a2a5a57",
                    "url": "https://api.github.com/repos/cython/cython/git/trees/e2a275d5adb4d4afa28d6987b364bb244a2a5a57"
                },
                "url": "https://api.github.com/repos/cython/cython/git/commits/491434fff8477e1a76926515600c45e45329c30c",
                "verification": {
                    "payload": null,
                    "reason": "unsigned",
                    "signature": null,
                    "verified": false,
                    "verified_at": null
                }
            },
            "committer": {
                "avatar_url": "https://avatars.githubusercontent.com/u/10536947?v=4",
                "events_url": "https://api.github.com/users/da-woods/events{/privacy}",
                "followers_url": "https://api.github.com/users/da-woods/followers",
                "following_url": "https://api.github.com/users/da-woods/following{/other_user}",
                "gists_url": "https://api.github.com/users/da-woods/gists{/gist_id}",
                "gravatar_id": "",
                "html_url": "https://github.com/da-woods",
                "id": 10536947,
                "login": "da-woods",
                "node_id": "MDQ6VXNlcjEwNTM2OTQ3",
                "organizations_url": "https://api.github.com/users/da-woods/orgs",
                "received_events_url": "https://api.github.com/users/da-woods/received_events",
                "repos_url": "https://api.github.com/users/da-woods/repos",
                "site_admin": false,
                "starred_url": "https://api.github.com/users/da-woods/starred{/owner}{/repo}",
                "subscriptions_url": "https://api.github.com/users/da-woods/subscriptions",
                "type": "User",
                "url": "https://api.github.com/users/da-woods",
                "user_view_type": "public"
            },
            "html_url": "https://github.com/cython/cython/commit/491434fff8477e1a76926515600c45e45329c30c",
            "node_id": "C_kwDOAhr4b9oAKDQ5MTQzNGZmZjg0NzdlMWE3NjkyNjUxNTYwMGM0NWU0NTMyOWMzMGM",
            "parents": [
                {
                    "html_url": "https://github.com/cython/cython/commit/66e708a464643385413e0ca9e94a15884e04bd84",
                    "sha": "66e708a464643385413e0ca9e94a15884e04bd84",
                    "url": "https://api.github.com/repos/cython/cython/commits/66e708a464643385413e0ca9e94a15884e04bd84"
                }
            ],
            "sha": "491434fff8477e1a76926515600c45e45329c30c",
            "url": "https://api.github.com/repos/cython/cython/commits/491434fff8477e1a76926515600c45e45329c30c"
        },
        {
            "author": {
                "avatar_url": "https://avatars.githubusercontent.com/u/10536947?v=4",
                "events_url": "https://api.github.com/users/da-woods/events{/privacy}",
                "followers_url": "https://api.github.com/users/da-woods/followers",
                "following_url": "https://api.github.com/users/da-woods/following{/other_user}",
                "gists_url": "https://api.github.com/users/da-woods/gists{/gist_id}",
                "gravatar_id": "",
                "html_url": "https://github.com/da-woods",
                "id": 10536947,
                "login": "da-woods",
                "node_id": "MDQ6VXNlcjEwNTM2OTQ3",
                "organizations_url": "https://api.github.com/users/da-woods/orgs",
                "received_events_url": "https://api.github.com/users/da-woods/received_events",
                "repos_url": "https://api.github.com/users/da-woods/repos",
                "site_admin": false,
                "starred_url": "https://api.github.com/users/da-woods/starred{/owner}{/repo}",
                "subscriptions_url": "https://api.github.com/users/da-woods/subscriptions",
                "type": "User",
                "url": "https://api.github.com/users/da-woods",
                "user_view_type": "public"
            },
            "comments_url": "https://api.github.com/repos/cython/cython/commits/9cec077741b567109aeff3f94a15a107d776364e/comments",
            "commit": {
                "author": {
                    "date": "2025-05-26T17:19:11Z",
                    "email": "dw-git@d-woods.co.uk",
                    "name": "da-woods"
                },
                "comment_count": 0,
                "committer": {
                    "date": "2025-05-26T17:19:11Z",
                    "email": "dw-git@d-woods.co.uk",
                    "name": "da-woods"
                },
                "message": "Only pass \"deprecated\" when it'll be understood",
                "tree": {
                    "sha": "c28ade34d6977c9c632c47b4c157a6b6670596fd",
                    "url": "https://api.github.com/repos/cython/cython/git/trees/c28ade34d6977c9c632c47b4c157a6b6670596fd"
                },
                "url": "https://api.github.com/repos/cython/cython/git/commits/9cec077741b567109aeff3f94a15a107d776364e",
                "verification": {
                    "payload": null,
                    "reason": "unsigned",
                    "signature": null,
                    "verified": false,
                    "verified_at": null
                }
            },
            "committer": {
                "avatar_url": "https://avatars.githubusercontent.com/u/10536947?v=4",
                "events_url": "https://api.github.com/users/da-woods/events{/privacy}",
                "followers_url": "https://api.github.com/users/da-woods/followers",
                "following_url": "https://api.github.com/users/da-woods/following{/other_user}",
                "gists_url": "https://api.github.com/users/da-woods/gists{/gist_id}",
                "gravatar_id": "",
                "html_url": "https://github.com/da-woods",
                "id": 10536947,
                "login": "da-woods",
                "node_id": "MDQ6VXNlcjEwNTM2OTQ3",
                "organizations_url": "https://api.github.com/users/da-woods/orgs",
                "received_events_url": "https://api.github.com/users/da-woods/received_events",
                "repos_url": "https://api.github.com/users/da-woods/repos",
                "site_admin": false,
                "starred_url": "https://api.github.com/users/da-woods/starred{/owner}{/repo}",
                "subscriptions_url": "https://api.github.com/users/da-woods/subscriptions",
                "type": "User",
                "url": "https://api.github.com/users/da-woods",
                "user_view_type": "public"
            },
            "html_url": "https://github.com/cython/cython/commit/9cec077741b567109aeff3f94a15a107d776364e",
            "node_id": "C_kwDOAhr4b9oAKDljZWMwNzc3NDFiNTY3MTA5YWVmZjNmOTRhMTVhMTA3ZDc3NjM2NGU",
            "parents": [
                {
                    "html_url": "https://github.com/cython/cython/commit/491434fff8477e1a76926515600c45e45329c30c",
                    "sha": "491434fff8477e1a76926515600c45e45329c30c",
                    "url": "https://api.github.com/repos/cython/cython/commits/491434fff8477e1a76926515600c45e45329c30c"
                }
            ],
            "sha": "9cec077741b567109aeff3f94a15a107d776364e",
            "url": "https://api.github.com/repos/cython/cython/commits/9cec077741b567109aeff3f94a15a107d776364e"
        },
        {
            "author": {
                "avatar_url": "https://avatars.githubusercontent.com/u/10536947?v=4",
                "events_url": "https://api.github.com/users/da-woods/events{/privacy}",
                "followers_url": "https://api.github.com/users/da-woods/followers",
                "following_url": "https://api.github.com/users/da-woods/following{/other_user}",
                "gists_url": "https://api.github.com/users/da-woods/gists{/gist_id}",
                "gravatar_id": "",
                "html_url": "https://github.com/da-woods",
                "id": 10536947,
                "login": "da-woods",
                "node_id": "MDQ6VXNlcjEwNTM2OTQ3",
                "organizations_url": "https://api.github.com/users/da-woods/orgs",
                "received_events_url": "https://api.github.com/users/da-woods/received_events",
                "repos_url": "https://api.github.com/users/da-woods/repos",
                "site_admin": false,
                "starred_url": "https://api.github.com/users/da-woods/starred{/owner}{/repo}",
                "subscriptions_url": "https://api.github.com/users/da-woods/subscriptions",
                "type": "User",
                "url": "https://api.github.com/users/da-woods",
                "user_view_type": "public"
            },
            "comments_url": "https://api.github.com/repos/cython/cython/commits/d481a9bac6b0cd16aed2cf163f3be2a5e523e90a/comments",
            "commit": {
                "author": {
                    "date": "2025-05-26T20:00:53Z",
                    "email": "dw-git@d-woods.co.uk",
                    "name": "da-woods"
                },
                "comment_count": 0,
                "committer": {
                    "date": "2025-05-26T20:00:53Z",
                    "email": "noreply@github.com",
                    "name": "GitHub"
                },
                "message": "Apply suggestions from code review\n\nCo-authored-by: scoder <stefan_ml@behnel.de>",
                "tree": {
                    "sha": "a2b50f286d18d112d073866bb21c50cdf8d103c9",
                    "url": "https://api.github.com/repos/cython/cython/git/trees/a2b50f286d18d112d073866bb21c50cdf8d103c9"
                },
                "url": "https://api.github.com/repos/cython/cython/git/commits/d481a9bac6b0cd16aed2cf163f3be2a5e523e90a",
                "verification": {
                    "payload": "tree a2b50f286d18d112d073866bb21c50cdf8d103c9\nparent 9cec077741b567109aeff3f94a15a107d776364e\nauthor da-woods <dw-git@d-woods.co.uk> 1748289653 +0100\ncommitter GitHub <noreply@github.com> 1748289653 +0100\n\nApply suggestions from code review\n\nCo-authored-by: scoder <stefan_ml@behnel.de>",
                    "reason": "valid",
                    "signature": "-----BEGIN PGP SIGNATURE-----\n\nwsFcBAABCAAQBQJoNMh1CRC1aQ7uu5UhlAAAUK8QALDd2zcSoJrXIh55vr+O22E3\n/XB7fVsbHmNoc4fOGqVL8olAY9kk0elvnSXmaRpby4a0feZjRYgWjOGM2i2L5ChJ\n/VQTOfakZocQL7QfZbw77t99vwS4XfXO3n8ms2jcuTvfFg1N4gvQ4dm2LoI4IF5E\nfBbKYPwXq85Mh8MwGOe3IkozLd/hhE7gHT6lWTWXEyPelYig1DQ3m/FXPoWzdpSG\nMTIkD5XllrND7SzdhpkQKpc5USA6Sj1SY5vsJVKkjDMZr7OqR39x30LhXGyZwSxq\nqw2pQoBobcs4s50olN5dY6kWU2fNuYXkP5/yrLPPdDnPL3qyXAyduJWQTy5R+NSI\nn4C3YynM0fvhJoHoYyXdRA/O39JrO/rsj1ToKKvzP4rxtGY4o9qfWeYlvfZeNOWF\nPc7JwjkoiXpF7CKslNGEHcKNFXAiABPZGuxwoNRNa/bhgLEYDrNT1p7VfAtGTT0S\nNJ6m8YVhFKk35CxnxLGYGeLHaqG2smV5sXYvI8xCh1ZcdVkuhB3YJ4PxOmGOtQV+\nCsPVWhDNmanug3pcmhsrJec3eOK9DETvv5kqIPA8CbB+POEoRSD6iOCGTN7SRmcI\nARXy73I5qkdT2Ps1n/0lJks0ntfkKQwogE0gRYbtgI/WpllPIH9WvZVXF5mThG/s\nJUOzbVmPrDdDs2DyRSPt\n=LRUg\n-----END PGP SIGNATURE-----\n",
                    "verified": true,
                    "verified_at": "2025-05-26T20:00:57Z"
                }
            },
            "committer": {
                "avatar_url": "https://avatars.githubusercontent.com/u/19864447?v=4",
                "events_url": "https://api.github.com/users/web-flow/events{/privacy}",
                "followers_url": "https://api.github.com/users/web-flow/followers",
                "following_url": "https://api.github.com/users/web-flow/following{/other_user}",
                "gists_url": "https://api.github.com/users/web-flow/gists{/gist_id}",
                "gravatar_id": "",
                "html_url": "https://github.com/web-flow",
                "id": 19864447,
                "login": "web-flow",
                "node_id": "MDQ6VXNlcjE5ODY0NDQ3",
                "organizations_url": "https://api.github.com/users/web-flow/orgs",
                "received_events_url": "https://api.github.com/users/web-flow/received_events",
                "repos_url": "https://api.github.com/users/web-flow/repos",
                "site_admin": false,
                "starred_url": "https://api.github.com/users/web-flow/starred{/owner}{/repo}",
                "subscriptions_url": "https://api.github.com/users/web-flow/subscriptions",
                "type": "User",
                "url": "https://api.github.com/users/web-flow",
                "user_view_type": "public"
            },
            "html_url": "https://github.com/cython/cython/commit/d481a9bac6b0cd16aed2cf163f3be2a5e523e90a",
            "node_id": "C_kwDOAhr4b9oAKGQ0ODFhOWJhYzZiMGNkMTZhZWQyY2YxNjNmM2JlMmE1ZTUyM2U5MGE",
            "parents": [
                {
                    "html_url": "https://github.com/cython/cython/commit/9cec077741b567109aeff3f94a15a107d776364e",
                    "sha": "9cec077741b567109aeff3f94a15a107d776364e",
                    "url": "https://api.github.com/repos/cython/cython/commits/9cec077741b567109aeff3f94a15a107d776364e"
                }
            ],
            "sha": "d481a9bac6b0cd16aed2cf163f3be2a5e523e90a",
            "url": "https://api.github.com/repos/cython/cython/commits/d481a9bac6b0cd16aed2cf163f3be2a5e523e90a"
        },
        {
            "author": {
                "avatar_url": "https://avatars.githubusercontent.com/u/10536947?v=4",
                "events_url": "https://api.github.com/users/da-woods/events{/privacy}",
                "followers_url": "https://api.github.com/users/da-woods/followers",
                "following_url": "https://api.github.com/users/da-woods/following{/other_user}",
                "gists_url": "https://api.github.com/users/da-woods/gists{/gist_id}",
                "gravatar_id": "",
                "html_url": "https://github.com/da-woods",
                "id": 10536947,
                "login": "da-woods",
                "node_id": "MDQ6VXNlcjEwNTM2OTQ3",
                "organizations_url": "https://api.github.com/users/da-woods/orgs",
                "received_events_url": "https://api.github.com/users/da-woods/received_events",
                "repos_url": "https://api.github.com/users/da-woods/repos",
                "site_admin": false,
                "starred_url": "https://api.github.com/users/da-woods/starred{/owner}{/repo}",
                "subscriptions_url": "https://api.github.com/users/da-woods/subscriptions",
                "type": "User",
                "url": "https://api.github.com/users/da-woods",
                "user_view_type": "public"
            },
            "comments_url": "https://api.github.com/repos/cython/cython/commits/e23bfcbfa31c9bb467535f5b62f8dc0d22454419/comments",
            "commit": {
                "author": {
                    "date": "2025-05-26T20:01:51Z",
                    "email": "dw-git@d-woods.co.uk",
                    "name": "da-woods"
                },
                "comment_count": 0,
                "committer": {
                    "date": "2025-05-26T20:01:51Z",
                    "email": "dw-git@d-woods.co.uk",
                    "name": "da-woods"
                },
                "message": "Simplify \"no option\" fallback",
                "tree": {
                    "sha": "9ba1991856edc2f56ddd9b77478acd2b74442ddb",
                    "url": "https://api.github.com/repos/cython/cython/git/trees/9ba1991856edc2f56ddd9b77478acd2b74442ddb"
                },
                "url": "https://api.github.com/repos/cython/cython/git/commits/e23bfcbfa31c9bb467535f5b62f8dc0d22454419",
                "verification": {
                    "payload": null,
                    "reason": "unsigned",
                    "signature": null,
                    "verified": false,
                    "verified_at": null
                }
            },
            "committer": {
                "avatar_url": "https://avatars.githubusercontent.com/u/10536947?v=4",
                "events_url": "https://api.github.com/users/da-woods/events{/privacy}",
                "followers_url": "https://api.github.com/users/da-woods/followers",
                "following_url": "https://api.github.com/users/da-woods/following{/other_user}",
                "gists_url": "https://api.github.com/users/da-woods/gists{/gist_id}",
                "gravatar_id": "",
                "html_url": "https://github.com/da-woods",
                "id": 10536947,
                "login": "da-woods",
                "node_id": "MDQ6VXNlcjEwNTM2OTQ3",
                "organizations_url": "https://api.github.com/users/da-woods/orgs",
                "received_events_url": "https://api.github.com/users/da-woods/received_events",
                "repos_url": "https://api.github.com/users/da-woods/repos",
                "site_admin": false,
                "starred_url": "https://api.github.com/users/da-woods/starred{/owner}{/repo}",
                "subscriptions_url": "https://api.github.com/users/da-woods/subscriptions",
                "type": "User",
                "url": "https://api.github.com/users/da-woods",
                "user_view_type": "public"
            },
            "html_url": "https://github.com/cython/cython/commit/e23bfcbfa31c9bb467535f5b62f8dc0d22454419",
            "node_id": "C_kwDOAhr4b9oAKGUyM2JmY2JmYTMxYzliYjQ2NzUzNWY1YjYyZjhkYzBkMjI0NTQ0MTk",
            "parents": [
                {
                    "html_url": "https://github.com/cython/cython/commit/d481a9bac6b0cd16aed2cf163f3be2a5e523e90a",
                    "sha": "d481a9bac6b0cd16aed2cf163f3be2a5e523e90a",
                    "url": "https://api.github.com/repos/cython/cython/commits/d481a9bac6b0cd16aed2cf163f3be2a5e523e90a"
                }
            ],
            "sha": "e23bfcbfa31c9bb467535f5b62f8dc0d22454419",
            "url": "https://api.github.com/repos/cython/cython/commits/e23bfcbfa31c9bb467535f5b62f8dc0d22454419"
        }
    ],
    "commits_url": "https://api.github.com/repos/cython/cython/pulls/6917/commits",
    "created_at": "2025-05-26T13:59:10Z",
    "diff_url": "https://github.com/cython/cython/pull/6917.diff",
    "draft": false,
    "head": {
        "label": "da-woods:pick-limited-api-version-to-test",
        "ref": "pick-limited-api-version-to-test",
        "repo": {
            "allow_forking": true,
            "archive_url": "https://api.github.com/repos/da-woods/cython/{archive_format}{/ref}",
            "archived": false,
            "assignees_url": "https://api.github.com/repos/da-woods/cython/assignees{/user}",
            "blobs_url": "https://api.github.com/repos/da-woods/cython/git/blobs{/sha}",
            "branches_url": "https://api.github.com/repos/da-woods/cython/branches{/branch}",
            "clone_url": "https://github.com/da-woods/cython.git",
            "collaborators_url": "https://api.github.com/repos/da-woods/cython/collaborators{/collaborator}",
            "comments_url": "https://api.github.com/repos/da-woods/cython/comments{/number}",
            "commits_url": "https://api.github.com/repos/da-woods/cython/commits{/sha}",
            "compare_url": "https://api.github.com/repos/da-woods/cython/compare/{base}...{head}",
            "contents_url": "https://api.github.com/repos/da-woods/cython/contents/{+path}",
            "contributors_url": "https://api.github.com/repos/da-woods/cython/contributors",
            "created_at": "2015-05-09T08:55:00Z",
            "default_branch": "master",
            "deployments_url": "https://api.github.com/repos/da-woods/cython/deployments",
            "description": "A Python to C compiler",
            "disabled": false,
            "downloads_url": "https://api.github.com/repos/da-woods/cython/downloads",
            "events_url": "https://api.github.com/repos/da-woods/cython/events",
            "fork": true,
            "forks": 0,
            "forks_count": 0,
            "forks_url": "https://api.github.com/repos/da-woods/cython/forks",
            "full_name": "da-woods/cython",
            "git_commits_url": "https://api.github.com/repos/da-woods/cython/git/commits{/sha}",
            "git_refs_url": "https://api.github.com/repos/da-woods/cython/git/refs{/sha}",
            "git_tags_url": "https://api.github.com/repos/da-woods/cython/git/tags{/sha}",
            "git_url": "git://github.com/da-woods/cython.git",
            "has_discussions": false,
            "has_downloads": true,
            "has_issues": false,
            "has_pages": false,
            "has_projects": true,
            "has_wiki": true,
            "homepage": "http://cython.org",
            "hooks_url": "https://api.github.com/repos/da-woods/cython/hooks",
            "html_url": "https://github.com/da-woods/cython",
            "id": 35321967,
            "is_template": false,
            "issue_comment_url": "https://api.github.com/repos/da-woods/cython/issues/comments{/number}",
            "issue_events_url": "https://api.github.com/repos/da-woods/cython/issues/events{/number}",
            "issues_url": "https://api.github.com/repos/da-woods/cython/issues{/number}",
            "keys_url": "https://api.github.com/repos/da-woods/cython/keys{/key_id}",
            "labels_url": "https://api.github.com/repos/da-woods/cython/labels{/name}",
            "language": "Python",
            "languages_url": "https://api.github.com/repos/da-woods/cython/languages",
            "license": {
                "key": "apache-2.0",
                "name": "Apache License 2.0",
                "node_id": "MDc6TGljZW5zZTI=",
                "spdx_id": "Apache-2.0",
                "url": "https://api.github.com/licenses/apache-2.0"
            },
            "merges_url": "https://api.github.com/repos/da-woods/cython/merges",
            "milestones_url": "https://api.github.com/repos/da-woods/cython/milestones{/number}",
            "mirror_url": null,
            "name": "cython",
            "node_id": "MDEwOlJlcG9zaXRvcnkzNTMyMTk2Nw==",
            "notifications_url": "https://api.github.com/repos/da-woods/cython/notifications{?since,all,participating}",
            "open_issues": 2,
            "open_issues_count": 2,
            "owner": {
                "avatar_url": "https://avatars.githubusercontent.com/u/10536947?v=4",
                "events_url": "https://api.github.com/users/da-woods/events{/privacy}",
                "followers_url": "https://api.github.com/users/da-woods/followers",
                "following_url": "https://api.github.com/users/da-woods/following{/other_user}",
                "gists_url": "https://api.github.com/users/da-woods/gists{/gist_id}",
                "gravatar_id": "",
                "html_url": "https://github.com/da-woods",
                "id": 10536947,
                "login": "da-woods",
                "node_id": "MDQ6VXNlcjEwNTM2OTQ3",
                "organizations_url": "https://api.github.com/users/da-woods/orgs",
                "received_events_url": "https://api.github.com/users/da-woods/received_events",
                "repos_url": "https://api.github.com/users/da-woods/repos",
                "site_admin": false,
                "starred_url": "https://api.github.com/users/da-woods/starred{/owner}{/repo}",
                "subscriptions_url": "https://api.github.com/users/da-woods/subscriptions",
                "type": "User",
                "url": "https://api.github.com/users/da-woods",
                "user_view_type": "public"
            },
            "private": false,
            "pulls_url": "https://api.github.com/repos/da-woods/cython/pulls{/number}",
            "pushed_at": "2025-05-27T09:22:17Z",
            "releases_url": "https://api.github.com/repos/da-woods/cython/releases{/id}",
            "size": 79145,
            "ssh_url": "git@github.com:da-woods/cython.git",
            "stargazers_count": 2,
            "stargazers_url": "https://api.github.com/repos/da-woods/cython/stargazers",
            "statuses_url": "https://api.github.com/repos/da-woods/cython/statuses/{sha}",
            "subscribers_url": "https://api.github.com/repos/da-woods/cython/subscribers",
            "subscription_url": "https://api.github.com/repos/da-woods/cython/subscription",
            "svn_url": "https://github.com/da-woods/cython",
            "tags_url": "https://api.github.com/repos/da-woods/cython/tags",
            "teams_url": "https://api.github.com/repos/da-woods/cython/teams",
            "topics": [],
            "trees_url": "https://api.github.com/repos/da-woods/cython/git/trees{/sha}",
            "updated_at": "2025-03-12T23:15:39Z",
            "url": "https://api.github.com/repos/da-woods/cython",
            "visibility": "public",
            "watchers": 2,
            "watchers_count": 2,
            "web_commit_signoff_required": false
        },
        "sha": "e23bfcbfa31c9bb467535f5b62f8dc0d22454419",
        "user": {
            "avatar_url": "https://avatars.githubusercontent.com/u/10536947?v=4",
            "events_url": "https://api.github.com/users/da-woods/events{/privacy}",
            "followers_url": "https://api.github.com/users/da-woods/followers",
            "following_url": "https://api.github.com/users/da-woods/following{/other_user}",
            "gists_url": "https://api.github.com/users/da-woods/gists{/gist_id}",
            "gravatar_id": "",
            "html_url": "https://github.com/da-woods",
            "id": 10536947,
            "login": "da-woods",
            "node_id": "MDQ6VXNlcjEwNTM2OTQ3",
            "organizations_url": "https://api.github.com/users/da-woods/orgs",
            "received_events_url": "https://api.github.com/users/da-woods/received_events",
            "repos_url": "https://api.github.com/users/da-woods/repos",
            "site_admin": false,
            "starred_url": "https://api.github.com/users/da-woods/starred{/owner}{/repo}",
            "subscriptions_url": "https://api.github.com/users/da-woods/subscriptions",
            "type": "User",
            "url": "https://api.github.com/users/da-woods",
            "user_view_type": "public"
        }
    },
    "html_url": "https://github.com/cython/cython/pull/6917",
    "id": 2544180231,
    "issue_url": "https://api.github.com/repos/cython/cython/issues/6917",
    "labels": [
        {
            "color": "444444",
            "default": false,
            "description": null,
            "id": 425558326,
            "name": "Testing",
            "node_id": "MDU6TGFiZWw0MjU1NTgzMjY=",
            "url": "https://api.github.com/repos/cython/cython/labels/Testing"
        },
        {
            "color": "F5AB5D",
            "default": false,
            "description": "",
            "id": 4210073287,
            "name": "limited api",
            "node_id": "LA_kwDOABDGAc768J7H",
            "url": "https://api.github.com/repos/cython/cython/labels/limited%20api"
        }
    ],
    "locked": false,
    "merge_commit_sha": "12e350ff8715fe81caa0892a0c212b8689583fb8",
    "merged_at": "2025-05-26T22:02:55Z",
    "milestone": {
        "closed_at": null,
        "closed_issues": 10,
        "created_at": "2020-02-09T13:21:48Z",
        "creator": {
            "avatar_url": "https://avatars.githubusercontent.com/u/491659?v=4",
            "events_url": "https://api.github.com/users/scoder/events{/privacy}",
            "followers_url": "https://api.github.com/users/scoder/followers",
            "following_url": "https://api.github.com/users/scoder/following{/other_user}",
            "gists_url": "https://api.github.com/users/scoder/gists{/gist_id}",
            "gravatar_id": "",
            "html_url": "https://github.com/scoder",
            "id": 491659,
            "login": "scoder",
            "node_id": "MDQ6VXNlcjQ5MTY1OQ==",
            "organizations_url": "https://api.github.com/users/scoder/orgs",
            "received_events_url": "https://api.github.com/users/scoder/received_events",
            "repos_url": "https://api.github.com/users/scoder/repos",
            "site_admin": false,
            "starred_url": "https://api.github.com/users/scoder/starred{/owner}{/repo}",
            "subscriptions_url": "https://api.github.com/users/scoder/subscriptions",
            "type": "User",
            "url": "https://api.github.com/users/scoder",
            "user_view_type": "public"
        },
        "description": "First feature release after the cleanup releases 3.0 and 3.1.",
        "due_on": null,
        "html_url": "https://github.com/cython/cython/milestone/75",
        "id": 5085425,
        "labels_url": "https://api.github.com/repos/cython/cython/milestones/75/labels",
        "node_id": "MDk6TWlsZXN0b25lNTA4NTQyNQ==",
        "number": 75,
        "open_issues": 20,
        "state": "open",
        "title": "3.2",
        "updated_at": "2025-05-27T09:04:51Z",
        "url": "https://api.github.com/repos/cython/cython/milestones/75"
    },
    "node_id": "PR_kwDOABDGAc6XpRwH",
    "number": 6917,
    "patch_url": "https://github.com/cython/cython/pull/6917.patch",
    "requested_reviewers": [],
    "requested_teams": [],
    "review_comment_url": "https://api.github.com/repos/cython/cython/pulls/comments{/number}",
    "review_comments_url": "https://api.github.com/repos/cython/cython/pulls/6917/comments",
    "state": "closed",
    "statuses_url": "https://api.github.com/repos/cython/cython/statuses/e23bfcbfa31c9bb467535f5b62f8dc0d22454419",
    "title": "Add an option to runtests to run with a specific Limited API version",
    "updated_at": "2025-05-27T05:49:11Z",
    "url": "https://api.github.com/repos/cython/cython/pulls/6917",
    "user": {
        "avatar_url": "https://avatars.githubusercontent.com/u/10536947?v=4",
        "events_url": "https://api.github.com/users/da-woods/events{/privacy}",
        "followers_url": "https://api.github.com/users/da-woods/followers",
        "following_url": "https://api.github.com/users/da-woods/following{/other_user}",
        "gists_url": "https://api.github.com/users/da-woods/gists{/gist_id}",
        "gravatar_id": "",
        "html_url": "https://github.com/da-woods",
        "id": 10536947,
        "login": "da-woods",
        "node_id": "MDQ6VXNlcjEwNTM2OTQ3",
        "organizations_url": "https://api.github.com/users/da-woods/orgs",
        "received_events_url": "https://api.github.com/users/da-woods/received_events",
        "repos_url": "https://api.github.com/users/da-woods/repos",
        "site_admin": false,
        "starred_url": "https://api.github.com/users/da-woods/starred{/owner}{/repo}",
        "subscriptions_url": "https://api.github.com/users/da-woods/subscriptions",
        "type": "User",
        "url": "https://api.github.com/users/da-woods",
        "user_view_type": "public"
    }
}